{"cameraMode":{"drawMode":0,"name":"Shaded","section":"Shading Mode"},"sceneLighting":true,"audioPlay":false,"sceneViewState":{"showFog":true,"showMaterialUpdate":false,"showSkybox":true,"showFlares":true,"showImageEffects":true,"showParticleSystems":true},"in2DMode":false,"pivot":{"x":-2.1708672046661379,"y":-0.4917524456977844,"z":0.07948722690343857},"rotation":{"x":-0.25027382373809817,"y":0.19359071552753449,"z":-0.05115089192986488,"w":-0.947245180606842},"size":123.885009765625,"orthographic":false}